ImageCompare/__init__.py
ImageCompare/CompareImage.py
ImageCompare/imagecompare.py
robotframework_imagecompare-0.2.0.dist-info/LICENSE
robotframework_imagecompare-0.2.0.dist-info/WHEEL
robotframework_imagecompare-0.2.0.dist-info/METADATA
robotframework_imagecompare-0.2.0.dist-info/RECORD
