Metadata-Version: 2.1
Name: robotframework-imagecompare
Version: 0.2.0
Summary: A Robot Framework Library for image comparisons
Home-page: https://github.com/manykarim/robotframework-imagecompare
License: Apache 2.0
Author: Many Kasiriha
Author-email: many.kasiriha@dbschenker.com
Requires-Python: >=3.8,<3.12
Classifier: License :: Other/Proprietary License
Classifier: Programming Language :: Python :: 3
Classifier: Programming Language :: Python :: 3.8
Classifier: Programming Language :: Python :: 3.9
Classifier: Programming Language :: Python :: 3.10
Classifier: Programming Language :: Python :: 3.11
Requires-Dist: imutils
Requires-Dist: numpy
Requires-Dist: opencv-python-headless
Requires-Dist: robotframework (>=4)
Requires-Dist: scikit-image
